fastalloc/__init__.py
fastalloc/__version__.py
fastalloc/decorators.py
fastalloc/exceptions.py
fastalloc/protocols.py
fastalloc/py.typed
fastalloc/types.py
fastalloc/utils.py
fastalloc/allocator/__init__.py
fastalloc/allocator/deque.py
fastalloc/allocator/freelist.py
fastalloc/allocator/stack.py
fastalloc/async_support/__init__.py
fastalloc/async_support/handle.py
fastalloc/async_support/pool.py
fastalloc/config/__init__.py
fastalloc/config/builder.py
fastalloc/config/growth_strategy.py
fastalloc/config/initialization.py
fastalloc/handle/__init__.py
fastalloc/handle/context.py
fastalloc/handle/owned.py
fastalloc/handle/weak.py
fastalloc/pool/__init__.py
fastalloc/pool/base.py
fastalloc/pool/fixed.py
fastalloc/pool/growing.py
fastalloc/pool/thread_local.py
fastalloc/pool/thread_safe.py
fastalloc/stats/__init__.py
fastalloc/stats/collector.py
fastalloc/stats/reporter.py
fastalloc-0.1.1.dist-info/licenses/LICENSE-APACHE
fastalloc-0.1.1.dist-info/licenses/LICENSE-MIT
fastalloc-0.1.1.dist-info/METADATA
fastalloc-0.1.1.dist-info/WHEEL
fastalloc-0.1.1.dist-info/top_level.txt
fastalloc-0.1.1.dist-info/RECORD
