Metadata-Version: 2.4
Name: fastalloc
Version: 0.1.1
Summary: High-performance Python memory pool library for pre-allocated object pooling
Home-page: https://gitlab.com/TIVisionOSS/python/fastalloc
Author: Eshan Roy
Author-email: Eshan Roy <eshanized@proton.me>
Maintainer-email: Eshan Roy <eshanized@proton.me>
License: MIT OR Apache-2.0
Project-URL: Homepage, https://gitlab.com/TIVisionOSS/python/fastalloc
Project-URL: Repository, https://gitlab.com/TIVisionOSS/python/fastalloc
Project-URL: Documentation, https://gitlab.com/TIVisionOSS/python/fastalloc/-/tree/main/docs
Project-URL: Bug Tracker, https://gitlab.com/TIVisionOSS/python/fastalloc/-/issues
Project-URL: Changelog, https://gitlab.com/TIVisionOSS/python/fastalloc/-/blob/main/CHANGELOG.md
Keywords: memory-pool,object-pool,performance,allocation,gc,garbage-collection,optimization,async,thread-safe
Classifier: Development Status :: 4 - Beta
Classifier: Intended Audience :: Developers
Classifier: License :: OSI Approved :: MIT License
Classifier: License :: OSI Approved :: Apache Software License
Classifier: Operating System :: OS Independent
Classifier: Programming Language :: Python :: 3
Classifier: Programming Language :: Python :: 3.8
Classifier: Programming Language :: Python :: 3.9
Classifier: Programming Language :: Python :: 3.10
Classifier: Programming Language :: Python :: 3.11
Classifier: Programming Language :: Python :: 3.12
Classifier: Programming Language :: Python :: Implementation :: CPython
Classifier: Topic :: Software Development :: Libraries :: Python Modules
Classifier: Topic :: Software Development :: Libraries
Classifier: Topic :: Utilities
Classifier: Typing :: Typed
Requires-Python: >=3.8
License-File: LICENSE-APACHE
License-File: LICENSE-MIT
Provides-Extra: numpy
Requires-Dist: numpy>=1.19.0; extra == "numpy"
Provides-Extra: dev
Requires-Dist: black>=23.0.0; extra == "dev"
Requires-Dist: isort>=5.12.0; extra == "dev"
Requires-Dist: mypy>=1.0.0; extra == "dev"
Requires-Dist: pylint>=2.17.0; extra == "dev"
Requires-Dist: flake8>=6.0.0; extra == "dev"
Requires-Dist: pytest>=7.3.0; extra == "dev"
Requires-Dist: pytest-cov>=4.1.0; extra == "dev"
Requires-Dist: pytest-benchmark>=4.0.0; extra == "dev"
Requires-Dist: hypothesis>=6.75.0; extra == "dev"
Requires-Dist: sphinx>=6.2.0; extra == "dev"
Requires-Dist: sphinx-rtd-theme>=1.2.0; extra == "dev"
Dynamic: license-file
